maskering/__init__.py
maskering-0.0.1.dist-info/WHEEL
maskering-0.0.1.dist-info/METADATA
maskering-0.0.1.dist-info/RECORD
